{
  "12h": {
    "Argent": {
      "call": "LONG",
      "fav_pct": 0.56,
      "heure": "12h15",
      "max_fav_pct": 0.74
    },
    "Blé": {
      "call": "LONG",
      "fav_pct": 0.03,
      "heure": "12h15",
      "max_fav_pct": 0.05
    },
    "Café (Arabica)": {
      "call": "LONG",
      "fav_pct": -0.01,
      "heure": "12h15",
      "max_fav_pct": 0.3
    }
  },
  "18h": {
    "Argent": {
      "call": "LONG",
      "fav_pct": -0.01,
      "heure": "18h15",
      "max_fav_pct": 0.74
    },
    "Blé": {
      "call": "LONG",
      "fav_pct": -0.0,
      "heure": "18h15",
      "max_fav_pct": 0.05
    },
    "Café (Arabica)": {
      "call": "LONG",
      "fav_pct": 0.26,
      "heure": "18h15",
      "max_fav_pct": 0.3
    }
  },
  "base": "emission"
}
